setup.cfg
setup.py
praise/__init__.py
praise/adjective.py
praise/adverb.py
praise/exclamation.py
praise/smiley.py
praise/verb.py
praise/words.py
praise.egg-info/PKG-INFO
praise.egg-info/SOURCES.txt
praise.egg-info/dependency_links.txt
praise.egg-info/top_level.txt