Metadata-Version: 1.1
Name: praise
Version: 0.1
Summary: Praise it
Home-page: https://github.com/funtion/praise
Author: Shufang Xie
Author-email: xieshufang76@gmail.com
License: UNKNOWN
Download-URL: https://github.com/funtion/praise/archive/0.1.tar.gz
Keywords: praise,logging
Platform: UNKNOWN
